odoo8_addon_account_credit_control_payment_details-8.0.1.0.0-py2.7-nspkg.pth
odoo8_addon_account_credit_control_payment_details-8.0.1.0.0.dist-info/DESCRIPTION.rst
odoo8_addon_account_credit_control_payment_details-8.0.1.0.0.dist-info/METADATA
odoo8_addon_account_credit_control_payment_details-8.0.1.0.0.dist-info/RECORD
odoo8_addon_account_credit_control_payment_details-8.0.1.0.0.dist-info/WHEEL
odoo8_addon_account_credit_control_payment_details-8.0.1.0.0.dist-info/metadata.json
odoo8_addon_account_credit_control_payment_details-8.0.1.0.0.dist-info/namespace_packages.txt
odoo8_addon_account_credit_control_payment_details-8.0.1.0.0.dist-info/top_level.txt
odoo_addons/account_credit_control_payment_details/README.rst
odoo_addons/account_credit_control_payment_details/__init__.py
odoo_addons/account_credit_control_payment_details/__openerp__.py
odoo_addons/account_credit_control_payment_details/i18n/it.po
odoo_addons/account_credit_control_payment_details/static/description/icon.png
odoo_addons/account_credit_control_payment_details/tests/__init__.py
odoo_addons/account_credit_control_payment_details/tests/test_credit_control_payment_details.py
odoo_addons/account_credit_control_payment_details/views/report_credit_control_summary.xml
